vehicle_lang/_temporary_files.py
vehicle_lang/error.py
vehicle_lang/_version.py
vehicle_lang/__init__.py
vehicle_lang/_binding.pyi
vehicle_lang/py.typed
vehicle_lang/binding.def
vehicle_lang/binding.i
vehicle_lang/typing.py
vehicle_lang/_binding.cpython-311-darwin.so
vehicle_lang/binding.py
vehicle_lang/__main__.py
vehicle_lang/_deps.py
vehicle_lang/validate/__init__.py
vehicle_lang/pygments/__init__.py
vehicle_lang/pygments/_external/__init__.py
vehicle_lang/loss/error.py
vehicle_lang/loss/_common.py
vehicle_lang/loss/__init__.py
vehicle_lang/loss/tensorflow.py
vehicle_lang/loss/_collections.py
vehicle_lang/loss/pytorch.py
vehicle_lang/loss/_numeric.py
vehicle_lang/loss/_pytorch/__init__.py
vehicle_lang/loss/_pytorch/_builtins.py
vehicle_lang/loss/_pytorch/_translation.py
vehicle_lang/loss/_pytorch/samplers.py
vehicle_lang/loss/_ast/_decode.py
vehicle_lang/loss/_ast/__init__.py
vehicle_lang/loss/_ast/_nodes.py
vehicle_lang/loss/_tensorflow/__init__.py
vehicle_lang/loss/_tensorflow/_builtins.py
vehicle_lang/loss/_tensorflow/_translation.py
vehicle_lang/loss/_tensorflow/samplers.py
vehicle_lang/loss/_abc/_types.py
vehicle_lang/loss/_abc/__init__.py
vehicle_lang/loss/_abc/_builtins.py
vehicle_lang/loss/_abc/_translation.py
vehicle_lang/loss/_abc/_samplers.py
vehicle_lang/loss/_python/__init__.py
vehicle_lang/loss/_python/_translation.py
vehicle_lang/verify/__init__.py
vehicle_lang/compile/__init__.py
vehicle_lang/list/__init__.py
vehicle_lang/typecheck/__init__.py
vehicle_lang/export/__init__.py
vehicle_lang/session/error.py
vehicle_lang/session/_functions.py
vehicle_lang/session/__init__.py
vehicle_lang/session/_session.py
vehicle_lang-0.23.0.dist-info/RECORD
vehicle_lang-0.23.0.dist-info/WHEEL
vehicle_lang-0.23.0.dist-info/entry_points.txt
vehicle_lang-0.23.0.dist-info/top_level.txt
vehicle_lang-0.23.0.dist-info/METADATA
vehicle_lang-0.23.0.dist-info/licenses/LICENSE
