Metadata-Version: 2.4
Name: vehicle_lang
Version: 0.23.0
Summary: A high-level functional language for writing mathematically-precise specifications for neural networks.
Author-email: Wen Kokke <wenkokke@users.noreply.github.com>
License-Expression: MIT
Requires-Python: <3.14,>=3.10
License-File: LICENSE
Requires-Dist: typing-extensions<5,>=4.6
Requires-Dist: jaxtyping<0.4,>=0.2
Requires-Dist: pytest>=8.4.2
Requires-Dist: pre-commit>=4.3.0
Provides-Extra: test
Requires-Dist: pytest<10,>=7.1; extra == "test"
Requires-Dist: packaging>=23; extra == "test"
Requires-Dist: pygments<3,>=2.14; extra == "test"
Requires-Dist: numpy<3,>=1.21; extra == "test"
Provides-Extra: mypy
Requires-Dist: types-setuptools>=45; extra == "mypy"
Requires-Dist: types-pygments<3,>=2.14; extra == "mypy"
Provides-Extra: pygments
Requires-Dist: pygments<3,>=2.14; extra == "pygments"
Provides-Extra: numpy
Requires-Dist: numpy<3,>=1.21; extra == "numpy"
Provides-Extra: jax
Requires-Dist: jax>=0.4.26; extra == "jax"
Provides-Extra: dev
Requires-Dist: pre-commit>=4.3.0; extra == "dev"
Provides-Extra: wheel
Requires-Dist: build; extra == "wheel"
Requires-Dist: auditwheel; sys_platform == "linux" and extra == "wheel"
Requires-Dist: delocate; sys_platform == "darwin" and extra == "wheel"
Provides-Extra: tensorflow
Requires-Dist: tensorflow<3,>=2; ((python_version >= "3.10" and python_version < "3.13") and ((sys_platform == "linux" and (platform_machine == "x86_64" or platform_machine == "aarch64")) or (sys_platform == "darwin" and platform_machine == "x86_64") or (sys_platform == "win32" and platform_machine == "AMD64"))) and extra == "tensorflow"
Provides-Extra: pytorch
Requires-Dist: torch<3,>=2; (python_version >= "3.10" and python_version < "3.13") and extra == "pytorch"
Dynamic: license-file
